MANIFEST.in
README.md
setup.py
flask_memcache_session/__init__.py
flask_memcache_session/session.py
flask_memcache_session.egg-info/PKG-INFO
flask_memcache_session.egg-info/SOURCES.txt
flask_memcache_session.egg-info/dependency_links.txt
flask_memcache_session.egg-info/top_level.txt