Metadata-Version: 1.0
Name: flask-memcache-session
Version: 2.0
Summary: Use memcache for store session data
Home-page: https://github.com/unk2k/Flask-memcache-session
Author: Constantine Slednev
Author-email: c.slednev@gmail.com
License: BSD License
Platform: UNKNOWN
